{
  "tweet_created_at": "2026-04-01T10:13:55.000000Z",
  "id": 2039285120151196000,
  "id_str": "2039285120151195826",
  "type": "tweet",
  "conversation_id_str": "2039285120151195826",
  "community_id_str": null,
  "community_name": null,
  "text": null,
  "full_text": "https://t.co/sEipXKaYcN",
  "source": "<a href=\"https://mobile.twitter.com\" rel=\"nofollow\">Twitter Web App</a>",
  "truncated": false,
  "in_reply_to_status_id": null,
  "in_reply_to_status_id_str": null,
  "in_reply_to_user_id": null,
  "in_reply_to_user_id_str": null,
  "in_reply_to_screen_name": null,
  "user": {
    "id": 139994361,
    "id_str": "139994361",
    "name": "木下勝寿🔥東証プライム社長兼現役マーケター",
    "screen_name": "kinoppirx78",
    "location": "日本",
    "url": "https://www.youtube.com/@kitatatsu_hr",
    "description": "◉フォローしてください | 東証プライム上場(株)北の達人コーポレーションの社長兼WEBマーケター ｜著作累計40万部| 最新刊「戦わずして売る技術」https://t.co/qXxa2Wv3wc | WEBマーケ、経営、仕事術について毎日18時発信 | 一緒に日本一のWEBマーケ集団を作りたい人募集中。",
    "protected": false,
    "verified": true,
    "followers_count": 100772,
    "friends_count": 744,
    "listed_count": 940,
    "favourites_count": 17460,
    "statuses_count": 30062,
    "created_at": "2010-05-04T07:47:39.000000Z",
    "profile_banner_url": "https://pbs.twimg.com/profile_banners/139994361/1763428943",
    "profile_image_url_https": "https://pbs.twimg.com/profile_images/1990580040845963264/rxWL3RJU_normal.jpg",
    "can_dm": true,
    "affiliation_label": null
  },
  "quoted_status_id": null,
  "quoted_status_id_str": null,
  "is_quote_status": false,
  "quoted_status": null,
  "retweeted_status": null,
  "quote_count": 144,
  "reply_count": 14,
  "retweet_count": 271,
  "favorite_count": 1786,
  "views_count": 1809154,
  "bookmark_count": 1905,
  "lang": "zxx",
  "entities": {
    "hashtags": [],
    "symbols": [],
    "timestamps": [],
    "urls": [
      {
        "display_url": "x.com/i/article/2031…",
        "expanded_url": "http://x.com/i/article/2031889785225428992",
        "indices": [
          0,
          23
        ],
        "url": "https://t.co/sEipXKaYcN"
      }
    ],
    "user_mentions": [],
    "display_text_range": [
      0,
      23
    ]
  },
  "is_pinned": false,
  "article": {
    "published_at": "2026-04-01T10:13:55.000000Z",
    "id": 2039285120151196000,
    "id_str": "2039285120151195826",
    "title": "【管理職への昇進、おめでとう！】",
    "preview_text": "管理職への昇進、本当におめでとう。\nこれまでプレイヤーとして圧倒的な成果を出し、周囲の信頼を勝ち取ってきた君だからこそ、この椅子を手にすることができたのだと思う。",
    "cover_url": "https://pbs.twimg.com/media/HDK7l46aIAAUlTq.png",
    "content_state": {
      "blocks": [
        {
          "data": [],
          "entityRanges": [],
          "inlineStyleRanges": [
            {
              "length": 19,
              "offset": 473,
              "style": "Bold"
            },
            {
              "length": 28,
              "offset": 1134,
              "style": "Bold"
            }
          ],
          "key": "fsj7f",
          "text": "管理職への昇進、本当におめでとう。\nこれまでプレイヤーとして圧倒的な成果を出し、周囲の信頼を勝ち取ってきた君だからこそ、この椅子を手にすることができたのだと思う。\n\nしかし、これからマネジメントの道で大成するために、最初にどうしても伝えておきたいことがある。\n\n知っておいてほしいのは\n昇進は「上がった」のではなく、「競技が変わった」ということだ。\n\nよって、今回の昇進はゴールではなく、スタートだということになる\n\nしかも、ただのスタートではない。\nもっと正確に言えば、君は今、「プレイヤーのトップ層」から「管理職の末端」へ移ったのだ。\n\nここを勘違いしてはいけない。\n\nプレイヤーとして成果を出し、周囲から認められ、エースとして活躍してきた人ほど、昇進した瞬間に「自分はさらに上に行った」と感じやすい。\nだが実際には、競技が変わったのである。\n\n\nプレイヤーとして一流だったことと、管理職として一流になることは、まったく別の話だ。\nもし、プレイヤー時代のスーパースター気分のままで管理職になろうとすれば、それはもう出発点から間違っている。\n\n● 高校球児がプロに入ると何が起こるか\n\nたとえば、プロ野球選手を思い浮かべてほしい。\n\nプロになるような選手は、高校時代にはたいていエースで四番、そしてキャプテンだ。\n学校ではスーパースターで、誰よりも野球がうまい。周囲から一目置かれ、ちやほやされ、自分の判断が最も正しいと思っていても不思議ではない。実際、身の回りにいる誰よりも結果を出してきたのだから、その感覚自体は間違いではない。\n監督でさえ君に意見は言えなかっただろう。\n\nしかし、プロの世界に入った瞬間、景色は一変する。\n\nそこにいるのは、みな同じように高校時代のスターだった者たちだ。\n昨日まで特別だった人間が、今日からは「その中の一人」になる。\n\nここで大事なのは、気持ちを切り替えられるかどうかだ。\n\n高校時代の成功体験にしがみつき、「自分のやり方が一番正しい」「他人の言うことを聞く必要はない」と思い続ける人は、プロの世界で伸びない。\n高校時代の練習法、高校時代の感覚、高校時代のプライドを引きずったままでは、プロレベルの技術も思考も身につかないからだ。\n\n結果として、いつまでも二軍から抜け出せない。\n肩書きだけは「プロ野球選手」だから、飲み屋で「この人、プロなんだよ」と紹介されれば「すごい！」とは言われるかもしれない。だが、本当に勝負すべき場所では、何も残せない。\n\n管理職への昇進も、これとよく似ている。\n\nプレイヤーとしてどれだけ優秀でも、管理職としてはまだ新人だ。\nまずはその現実を受け入れ、学び、鍛え直すことから始めなければならない。\n\n● 起業家も同じ。「エース社員」から「底辺経営者」になる\n\nこれはベンチャー起業家にもよく似た構図がある。\n\n大手企業や有名企業で優秀な成績を残し、満を持して独立する人がいる。\n社内では誰もが認めるエース社員だったのだろう。\n\nだが、起業した瞬間に起こることは、実は昇進と同じだ。\nつまり、「エース社員」から「底辺経営者」になるのである。\n\n会社にいた頃は、看板も信用も実績もあった。\nだが独立後は違う。外部取引でも採用でも、相手から見れば「まだ何の実績もない会社の人」だ。\nだからこそ、一つひとつ信用を積み上げていかなければならない。\n\nところが、ここで失敗する人がいる。\n\nそれは、自分が「エース社員」ではなく「実績ゼロの経営者1年生」になったことを受け入れられない人だ。\n気持ちはいつまでもピカピカのエースのままでいたい。\nその欲望が、身の丈に合わない行動を生む。\n\nベンチャーキャピタルから資金を引っ張り、立派すぎるオフィスを構え、高額報酬で経歴のきらびやかな社員を集める。\nだが、肝心の会社にはまだ実績がない。中身ができていない。\n\nそういう“ハリボテ起業家”は、時間がたてばすぐに化けの皮が剥がれる。\n土台のない見栄は、長くは持たない。\n\nこれも管理職と同じだ。\n\n役職がついたからといって、中身まで一気に管理職として完成するわけではない。\nむしろ最初は、肩書きだけが先についた状態だ。\nだからこそ、見栄を張るのではなく、実力を一つずつ積み上げる必要がある。\n\n\nここまでの話を一言でまとめるなら、こういうことだ。\n\n君はいま、偉くなったのではない。新しい職種の初心者になったのである。\n\nプレイヤーとして成果を出してきたことは誇っていい。\nそれは間違いなく君の努力の証明だし、会社が君を昇進させた理由でもある。\n\nしかし、その成功体験に酔ってはいけない。\n\n管理職に求められるのは、自分が結果を出す力だけではない。\n人を通じて成果を出す力だ。\nメンバーを育てる力だ。\n組織の空気をつくる力だ。\n仕組みを整え、再現性を高め、チームで勝つ力だ。\n\nつまり、武器が変わる。\n\nこれまで君は、自分の能力、自分のスピード、自分の努力量で戦ってきた。\nだが、これからはそれだけでは足りない。\nむしろ「自分ができること」が強すぎる人ほど、最初は苦労するかもしれない。\n\nなぜなら、自分でやったほうが早いからだ。\n自分のやり方のほうが正しいと思ってしまうからだ。\n部下の未熟さにイライラし、自分の優秀さを基準に周囲を見てしまうからだ。\n\nだが、それをやり続けた先にあるのは、強い管理職ではない。\nただの“プレイヤー気質が抜けない上司”である。\n\n\n新任管理職が最初にやるべきことは、格好をつけることではない。\n「管理職らしく見せる」ことでもない。\nましてや、プレイヤー時代の延長線上で自分のすごさを証明し続けることでもない。\n\n最初にやるべきは、自分はまだ未熟だと認めることだ。\n\n分からないことを学ぶ。\nうまくできないことを受け入れる。\n先輩管理職のやり方を吸収する。\n自分より経験のある人の意見を聞く。\n部下との関わり方を試し、失敗し、修正する。\n\nそうやって、一つずつ管理職としての筋力をつけていくしかない。\n\nプライドが邪魔をするかもしれない。\n「これまで結果を出してきた自分が、今さら初心者みたいに学ぶのか」と思うかもしれない。\n\nしかし、その姿勢こそが、君を本当に強い管理職にする。\n\n逆に言えば、ここで初心者になれない人は伸びない。\n過去の自分の栄光を脱げない人は、新しい役割で成長できない。\n\n本当に優秀な人とは、何をやっても自信満々な人ではない。\n立場が変われば、必要な姿勢まで変えられる人だ。\n\nプレイヤーのトップだった人が、管理職の末端に回ったとき、\n「自分はまだまだだ」\n「ここから学び直そう」\n「新しい競技で一から勝ち上がろう」\nと腹をくくれるかどうか。\n\nそこが分かれ目になる。\n\n昇進とは、過去の実績へのご褒美ではない。\n未来の責任への任命だ。\n\nだから、胸を張っていい。\nだが、ふんぞり返ってはいけない。\n\n自信は持っていい。\nだが、過信してはいけない。\n\n君がこれから目指すべきは、\n「優秀なプレイヤーだった管理職」ではなく、\n「本当に強い管理職」だ。\n\nそのために必要なのは、エース社員の自分にしがみつくことではない。\n一度それを脱ぎ捨てて、マネジメント初心者として出直す覚悟である。\n\n昇進おめでとう。\nここからが、本当のスタートだ。",
          "type": "unstyled"
        },
        {
          "data": [],
          "entityRanges": [],
          "inlineStyleRanges": [],
          "key": "261aa",
          "text": "※一人でも多くの新任管理職に届くように、よろしければリポストしてください。",
          "type": "unstyled"
        }
      ],
      "entityMap": []
    },
    "media_entities": []
  }
}